{
  "turtle": {
    "greenie": {
      "spriteID": "turtle",
      "scale": 1.0,
      "dimensions": [1, 1],
      "anchor": [0.5, 0.8],
      "animations": [
        {
          "name": "stand",
          "frames": [
            { "direction": 2, "frames": [0] },
            { "direction": 1, "frames": [1] },
            { "direction": 3, "frames": [2] },
            { "direction": 0, "frames": [3] }
          ]
        }
      ]
    },
    "greenie2": {
      "spriteID": "turtle",
      "scale": 1.0,
      "dimensions": [1, 1],
      "anchor": [0.5, 0.8],
      "animations": [
        {
          "name": "stand",
          "frames": [
            { "direction": 2, "frames": [0] },
            { "direction": 1, "frames": [1] },
            { "direction": 3, "frames": [2] },
            { "direction": 0, "frames": [3] }
          ]
        }
      ]
    }
  },
  "chair": {
    "chairBasic": {
      "spriteID": "tableandchair",
      "scale": 1,
      "dimensions": [1, 1],
      "anchor": [0.5, 0.5],
      "animations": [
        {
          "name": "stand",
          "frames": [
            {"direction": 2, "frames": [1]},
            {"direction": 1, "frames": [1]},
            {"direction": 3, "frames": [1]},
            {"direction": 0, "frames": [1]}
          ]
        }
      ]
    }
  },
  "table": {
    "tableBasic": {
      "spriteID": "tableandchair",
      "scale": 1,
      "dimensions": [2, 2],
      "anchor": [0.19, 0.25],
      "animations": [
        {
          "name": "stand",
          "frames": [
            {"direction": 2, "frames": [0]},
            {"direction": 1, "frames": [0]},
            {"direction": 3, "frames": [0]},
            {"direction": 0, "frames": [0]}
          ]
        }
      ]
    }
  },
  "door": {
    "doorBasic": {
      "spriteID": "tableandchair",
      "scale": 1,
      "dimensions": [1, 1],
      "anchor": [0.5, 0.5],
      "animations": [
        {
          "name": "stand",
          "frames": [
            {"direction": 2, "frames": [1]},
            {"direction": 1, "frames": [1]},
            {"direction": 3, "frames": [1]},
            {"direction": 0, "frames": [1]}
          ]
        }
      ]
    }
  }
}
